AI_envs/__init__.py
AI_envs/import_fix.py
AI_envs/pong.py
AI_envs-0.1.3.dist-info/LICENSE
AI_envs-0.1.3.dist-info/METADATA
AI_envs-0.1.3.dist-info/WHEEL
AI_envs-0.1.3.dist-info/top_level.txt
AI_envs-0.1.3.dist-info/RECORD
