Metadata-Version: 2.1
Name: AI-envs
Version: 0.1.3
Summary: Ambientes do gym
Home-page: https://github.com/rafa-per/AI-envs.git
Author: Rafael Pereira
Author-email: ranobrega@gmail.com
License: MIT
Project-URL: Source, https://github.com/rafa-per/AI-envs.git
Project-URL: Tracker, https://github.com/rafa-per/AI-envs.git/issues
Classifier: Programming Language :: Python :: 3
Classifier: License :: OSI Approved :: MIT License
License-File: LICENSE
Requires-Dist: pygame
Requires-Dist: gym ==0.17.2
